scripts/__VERSION__
scripts/update_version.py
vule_magics/__init__.py
vule_magics_python2-0.1.0.dist-info/METADATA
vule_magics_python2-0.1.0.dist-info/WHEEL
vule_magics_python2-0.1.0.dist-info/top_level.txt
vule_magics_python2-0.1.0.dist-info/RECORD
